guardescan/__init__.py
guardescan/advanced.py
guardescan/benchmark.py
guardescan/chains.py
guardescan/chains_enhanced.py
guardescan/cli.py
guardescan/core.py
guardescan/fixer.py
guardescan/reports.py
guardescan/scanner.py
guardescan/slither_engine.py
guardescan-5.0.0.dist-info/METADATA
guardescan-5.0.0.dist-info/WHEEL
guardescan-5.0.0.dist-info/entry_points.txt
guardescan-5.0.0.dist-info/top_level.txt
guardescan-5.0.0.dist-info/RECORD
