Metadata-Version: 2.4
Name: guardescan
Version: 5.0.0
Summary: The World's Most Powerful Smart Contract Security Scanner - Slither-Powered with DeFi & Multi-Chain Analysis
Author-email: Scorpius Security <security@scorpius.io>
Maintainer-email: Scorpius Security <security@scorpius.io>
License: MIT
Project-URL: Homepage, https://github.com/scorpius-security/scorpius-scanner
Project-URL: Documentation, https://github.com/scorpius-security/scorpius-scanner#readme
Project-URL: Repository, https://github.com/scorpius-security/scorpius-scanner
Project-URL: Issues, https://github.com/scorpius-security/scorpius-scanner/issues
Project-URL: Changelog, https://github.com/scorpius-security/scorpius-scanner/releases
Keywords: solidity,smart-contracts,security,vulnerability-scanner,ethereum,blockchain,defi,audit,static-analysis,slither,solana,rust,anchor,move,aptos,sui,cairo,starknet,cosmwasm,cosmos,polkadot,ink,near,multi-chain,web3,flash-loan,reentrancy,oracle-manipulation,sandwich-attack,mev
Classifier: Development Status :: 5 - Production/Stable
Classifier: Environment :: Console
Classifier: Intended Audience :: Developers
Classifier: Intended Audience :: Information Technology
Classifier: License :: OSI Approved :: MIT License
Classifier: Operating System :: OS Independent
Classifier: Programming Language :: Python :: 3
Classifier: Programming Language :: Python :: 3.8
Classifier: Programming Language :: Python :: 3.9
Classifier: Programming Language :: Python :: 3.10
Classifier: Programming Language :: Python :: 3.11
Classifier: Programming Language :: Python :: 3.12
Classifier: Programming Language :: Python :: 3.13
Classifier: Topic :: Security
Classifier: Topic :: Software Development :: Quality Assurance
Classifier: Topic :: Software Development :: Testing
Classifier: Topic :: Software Development :: Build Tools
Requires-Python: >=3.8
Provides-Extra: full
Requires-Dist: slither-analyzer>=0.9.0; extra == "full"
Provides-Extra: dev
Requires-Dist: pytest>=7.0.0; extra == "dev"
Requires-Dist: pytest-cov>=4.0.0; extra == "dev"
Requires-Dist: black>=23.0.0; extra == "dev"
Requires-Dist: ruff>=0.1.0; extra == "dev"
